__init__.py
hello.py
xebra-0.0.0.dist-info/METADATA
xebra-0.0.0.dist-info/WHEEL
xebra-0.0.0.dist-info/top_level.txt
xebra-0.0.0.dist-info/RECORD
